bootstrap_datepicker_plus/__init__.py
bootstrap_datepicker_plus/_base.py
bootstrap_datepicker_plus/_config.py
bootstrap_datepicker_plus/py.typed
bootstrap_datepicker_plus/schemas.py
bootstrap_datepicker_plus/settings.py
bootstrap_datepicker_plus/static/bootstrap_datepicker_plus/css/datepicker-widget.css
bootstrap_datepicker_plus/static/bootstrap_datepicker_plus/js/datepicker-widget.js
bootstrap_datepicker_plus/templates/bootstrap_datepicker_plus/input.html
bootstrap_datepicker_plus/widgets.py
django_bootstrap_datepicker_plus-5.0.6.dist-info/METADATA
django_bootstrap_datepicker_plus-5.0.6.dist-info/WHEEL
django_bootstrap_datepicker_plus-5.0.6.dist-info/licenses/LICENSE
django_bootstrap_datepicker_plus-5.0.6.dist-info/RECORD
