Metadata-Version: 2.4
Name: django-bootstrap-datepicker-plus
Version: 5.0.6
Summary: Bootstrap3/Bootstrap4/Bootstrap5 DatePickerInput, TimePickerInput, DateTimePickerInput, MonthPickerInput, YearPickerInput
License: MIT
License-File: LICENSE
Keywords: django,bootstrap,date-picker,time-picker,datetime-picker,date-range-picker
Author: Abdul Monim
Author-email: 6266677+monim67@users.noreply.github.com
Requires-Python: >=3.8,<4.0
Classifier: Development Status :: 5 - Production/Stable
Classifier: Environment :: Web Environment
Classifier: Framework :: Django
Classifier: Framework :: Django :: 2.0
Classifier: Framework :: Django :: 3.0
Classifier: Framework :: Django :: 4.0
Classifier: Framework :: Django :: 5.0
Classifier: Intended Audience :: Developers
Classifier: License :: OSI Approved :: MIT License
Classifier: Operating System :: OS Independent
Classifier: Programming Language :: Python :: 3
Classifier: Programming Language :: Python :: 3.8
Classifier: Programming Language :: Python :: 3.9
Classifier: Programming Language :: Python :: 3.10
Classifier: Programming Language :: Python :: 3.11
Classifier: Programming Language :: Python :: 3.12
Classifier: Programming Language :: Python :: 3.13
Classifier: Programming Language :: Python :: 3.14
Classifier: Topic :: Software Development :: Libraries
Classifier: Topic :: Utilities
Classifier: Typing :: Typed
Requires-Dist: Django (>=2,<6)
Requires-Dist: pydantic (>=1,<3)
Requires-Dist: typing-extensions (>=4.5,<5.0)
Project-URL: Documentation, https://django-bootstrap-datepicker-plus.readthedocs.io/en/latest/
Project-URL: Repository, https://github.com/monim67/django-bootstrap-datepicker-plus
